uqtie/UqtMav.py
uqtie/UqtStylesheet.py
uqtie/UqtWin.py
uqtie/__init__.py
uqtie-0.1.2.data/scripts/simple_uqtie.py
uqtie-0.1.2.dist-info/LICENSE
uqtie-0.1.2.dist-info/METADATA
uqtie-0.1.2.dist-info/WHEEL
uqtie-0.1.2.dist-info/top_level.txt
uqtie-0.1.2.dist-info/RECORD
