Metadata-Version: 2.1
Name: uqtie
Version: 0.1.2
Summary: Utilities for small or throwaway PyQt5 applications
Home-page: https://github.com/langrind/uqtie
Author: Nik Langrind
Author-email: langrind@gmail.com
License: MIT
Platform: UNKNOWN
Classifier: Programming Language :: Python :: 3
Classifier: License :: OSI Approved :: MIT License
Classifier: Operating System :: OS Independent
Requires-Python: >=3.6
